graphrs_python/_lib.abi3.so
graphrs_python/__init__.py
graphrs_python.libs/libblas-357956a1.so.3.4.2
graphrs_python.libs/libgfortran-91cc3cb1.so.3.0.0
graphrs_python.libs/libquadmath-96973f99.so.0.0.0
graphrs_python.libs/liblapack-1ad85175.so.3.4.2
graphrs_python-0.11.12.dist-info/top_level.txt
graphrs_python-0.11.12.dist-info/RECORD
graphrs_python-0.11.12.dist-info/LICENSE
graphrs_python-0.11.12.dist-info/METADATA
graphrs_python-0.11.12.dist-info/WHEEL
