Metadata-Version: 2.2
Name: graphrs_python
Version: 0.11.12
Summary: A Python module that wraps the high-performance `graphrs` Rust library.
Author-email: Malcolm van Raalte <malcolm@van.raalte.ca>
License: MIT License
Project-URL: Repository, https://github.com/malcolmvr/graphrs_python
Keywords: graph,network,graph theory,network theory,graph algorithms,network algorithms
Classifier: Development Status :: 5 - Production/Stable
Classifier: Intended Audience :: Developers
Classifier: License :: OSI Approved :: MIT License
Classifier: Programming Language :: Python :: 3
Classifier: Programming Language :: Rust
Classifier: Topic :: Scientific/Engineering :: Information Analysis
Classifier: Topic :: Scientific/Engineering :: Mathematics
Classifier: Topic :: Software Development :: Libraries
Classifier: Topic :: Software Development :: Libraries :: Python Modules
Classifier: Typing :: Typed
License-File: LICENSE
